metrictrees/__init__.py
metrictrees/bktree.py
metrictrees/py.typed
metrictrees-0.0.1.dist-info/METADATA
metrictrees-0.0.1.dist-info/WHEEL
metrictrees-0.0.1.dist-info/top_level.txt
metrictrees-0.0.1.dist-info/zip-safe
metrictrees-0.0.1.dist-info/RECORD
